README.md
setup.cfg
setup.py
python_sns_aws_client/__init__.py
python_sns_aws_client/constans.py
python_sns_aws_client/exceptions.py
python_sns_aws_client/test.py
python_sns_aws_client/utils.py
python_sns_aws_client.egg-info/PKG-INFO
python_sns_aws_client.egg-info/SOURCES.txt
python_sns_aws_client.egg-info/dependency_links.txt
python_sns_aws_client.egg-info/top_level.txt