Metadata-Version: 1.1
Name: python-sns-aws-client
Version: 1.3
Summary: use boto3 for send and receive sns-topic
Home-page: https://gitlab.com/Udalbert/python-sns-aws-python
Author: Zinobe
Author-email: udgottschalk@gmail.com
License: UNKNOWN
Download-URL: https://gitlab.com/Udalbert/python-sns-aws-python/tags/1.3
Keywords: boto3-python,sns-topic,aws-sns
Platform: UNKNOWN
Classifier: Programming Language :: Python
